[{"nid": 1710963490253, "word": "难倒", "meaning": "1. to baffle; 2. to confound; 3. to stump", "sentence": "这道数学题把我给难倒了。", "pinyin": "Zhè dào shùxué tí bǎ wǒ gěi nán dǎo le.", "english": "This math problem completely stumped me."}, {"nid": 1710963495347, "word": "存在主义", "meaning": "1. existentialism", "sentence": "他在大学时对存在主义很感兴趣。", "pinyin": "Tā zài dàxué shí duì cúnzài zhǔyì hěn gǎn xìngqù.", "english": "He was very interested in existentialism when he was in college."}, {"nid": 1706376756011, "word": "平板", "meaning": "tablet, iPad;Dull, monotonous&nbsp;", "sentence": "她用平板电脑看了一部电影。", "pinyin": "Tā yòng píngbǎn diànnǎo kànle yī bù diànyǐng.", "english": "She watched a movie on her tablet."}, {"nid": 1781538470003, "word": "季后赛", "meaning": "a playoff", "sentence": "我们队终于进入了今年的季后赛。", "pinyin": "Wǒmen duì zhōngyú jìnrùle jīnnián de jìhòusài.", "english": "Our team finally made it into this year's playoffs."}, {"nid": 1781538470005, "word": "年均", "meaning": "annual average (rate)", "sentence": "这个城市的年均气温约为十五度。", "pinyin": "Zhège chéngshì de niánjūn qìwēn yuē wéi shíwǔ dù.", "english": "The annual average temperature in this city is about fifteen degrees."}]