[{"nid": 1781538470203, "word": "边防", "meaning": "frontier defense", "sentence": "战士们在寒冷的冬天坚守边防，保卫国家。", "pinyin": "Zhàn shì men zài hán lěng de dōng tiān jiān shǒu biān fáng, bǎo wèi guó jiā.", "english": "The soldiers guard the frontier defense through the cold winter to protect the country."}, {"nid": 1781538470204, "word": "立法机关", "meaning": "legislature", "sentence": "新的法律需要经过立法机关审议通过。", "pinyin": "Xīn de fǎ lǜ xū yào jīng guò lì fǎ jī guān shěn yì tōng guò.", "english": "New laws must be reviewed and passed by the legislature."}, {"nid": 1717270485034, "word": "花卉", "meaning": "1. flowers and plants", "sentence": "阳台上摆了几盆花卉。", "pinyin": "Yángtái shàng bǎi le jǐ pén huāhuì.", "english": "A few pots of flowers and plants are arranged on the balcony."}, {"nid": 1537328246091, "word": "警车", "meaning": "Police car", "sentence": "街上停着一辆警车，引来很多人围观。", "pinyin": "Jiē shang tíng zhe yī liàng jǐng chē, yǐn lái hěn duō rén wéiguān.", "english": "A police car was parked on the street, drawing a crowd of onlookers."}, {"nid": 1537328248077, "word": "背着", "meaning": "To carry, memorize", "sentence": "他背着大包走了很远的路。", "pinyin": "Tā bèi zhe dà bāo zǒu le hěn yuǎn de lù.", "english": "He walked a long way carrying a large bag on his back."}]