[{"nid": 1537328244893, "word": "雨伞", "meaning": "Umbrella (for the rain)", "sentence": "出门别忘了带雨伞。", "pinyin": "Chūmén bié wàngle dài yǔsǎn.", "english": "Don't forget to bring an umbrella when you go out."}, {"nid": 1781538470138, "word": "小楼", "meaning": "small multi-story building; modest house with two or more floors", "sentence": "他在郊区买了一栋两层的小楼。", "pinyin": "Tā zài jiāoqū mǎi le yī dòng liǎng céng de xiǎo lóu.", "english": "He bought a small two-story house in the suburbs."}, {"nid": 1781538470140, "word": "留用", "meaning": "to keep for use; to retain sth; to keep sb in his job", "sentence": "公司决定把这位优秀员工留用。", "pinyin": "Gōngsī juédìng bǎ zhè wèi yōuxiù yuángōng liú yòng.", "english": "The company decided to retain this outstanding employee."}, {"nid": 1781538470142, "word": "投书", "meaning": "to submit a written piece (letter, article, opinion piece etc)", "sentence": "他向报社投书，反映小区停车问题。", "pinyin": "Tā xiàng bàoshè tóu shū, fǎnyìng xiǎoqū tíngchē wèntí.", "english": "He submitted a letter to the newspaper reflecting on the parking problems in his community."}, {"nid": 1781538470144, "word": "交通规则", "meaning": "traffic rules; rules of the road", "sentence": "开车一定要遵守交通规则。", "pinyin": "Kāi chē yīdìng yào zūnshǒu jiāo tōng guī zé.", "english": "You must always follow traffic rules when driving."}]