[{"nid": 1708747523654, "word": "据称", "meaning": "1. it is said; 2. allegedly; 3. according to reports; 4. or so they sa", "sentence": "据称这家餐厅的厨师曾在法国学艺。", "pinyin": "Jùchēng zhè jiā cāntīng de chúshī céng zài Fǎguó xuéyì.", "english": "It is said the chef at this restaurant once trained in France."}, {"nid": 1708747526349, "word": "入神", "meaning": "1. to be enthralled; 2. to be entranced", "sentence": "他看书看得入神，没听到我叫他。", "pinyin": "Tā kàn shū kàn de rùshén, méi tīngdào wǒ jiào tā.", "english": "He was so engrossed in his book that he didn't hear me call him."}, {"nid": 1710963487548, "word": "开源", "meaning": "1. to expand one&#x27;s financial resources; 2. abbr. for 開放源碼|开放源码[kā", "sentence": "这个软件是开源的，任何人都可以使用。", "pinyin": "Zhège ruǎnjiàn shì kāiyuán de, rènhé rén dōu kěyǐ shǐyòng.", "english": "This software is open-source and anyone can use it."}, {"nid": 1710963492818, "word": "选择性", "meaning": "1. selective; 2. selectiveness; 3. selectivity", "sentence": "他的记忆有很强的选择性。", "pinyin": "Tā de jìyì yǒu hěn qiáng de xuǎnzéxìng.", "english": "His memory is highly selective."}, {"nid": 1710963500865, "word": "部族", "meaning": "1. tribe; 2. tribal", "sentence": "这个部族世代住在山里。", "pinyin": "Zhège bùzú shìdài zhù zài shān lǐ.", "english": "This tribe has lived in the mountains for generations."}]