[{"nid": 1726793793988, "word": "高铁", "meaning": "high-speed rail", "sentence": "坐高铁从北京到上海只要四个多小时。", "pinyin": "Zuò gāotiě cóng Běijīng dào Shànghǎi zhǐyào sì gè duō xiǎoshí.", "english": "Taking the high-speed rail from Beijing to Shanghai takes just over four hours."}, {"nid": 1393817668449, "word": "理智", "meaning": "reason; intellect; rational", "sentence": "遇到困难时要保持理智，冷静分析。", "pinyin": "Yù dào kùnnán shí yào bǎochí lǐzhì, lěngjìng fēnxī.", "english": "When facing difficulties, stay rational and analyze calmly."}, {"nid": 1708747497161, "word": "全集", "meaning": "1. omnibus; 2. complete works (of a writer or artist)", "sentence": "我买了鲁迅全集，放在书架上。", "pinyin": "Wǒ mǎi le Lǔ Xùn quánjí, fàng zài shūjià shàng.", "english": "I bought the complete works of Lu Xun and placed them on the bookshelf."}, {"nid": 1708747514009, "word": "真真", "meaning": "1. really; 2. in fact; 3. genuinely; 4. scrupulously", "sentence": "这是真真发生过的事，不是故事。", "pinyin": "Zhè shì zhēnzhēn fāshēng guò de shì, bú shì gùshi.", "english": "This is something that really and truly happened, not a story."}, {"nid": 1781538469509, "word": "基本点", "meaning": "key point; crux; (finance) basis point, abbr. to 基點|基点[ji1 dian3]", "sentence": "利率下调了五十个基本点，贷款压力小多了。", "pinyin": "Lìlǜ xiàtiáo le wǔshí gè jīběndiǎn, dàikuǎn yālì xiǎo duō le.", "english": "The interest rate was cut by fifty basis points, so the loan burden is much lighter."}]