[{"nid": 1781538743635, "word": "联络人", "meaning": "(Tw) contact person", "sentence": "请把活动的联络人姓名发给我。", "pinyin": "Qǐng bǎ huódòng de liánluòrén xìngmíng fā gěi wǒ.", "english": "Please send me the name of the contact person for the event."}, {"nid": 1781538743638, "word": "声言", "meaning": "to state; to declare; pronouncement; declaration", "sentence": "他公开声言将继续坚持自己的立场。", "pinyin": "Tā gōngkāi shēngyán jiāng jìxù jiānchí zìjǐ de lìchǎng.", "english": "He publicly declared that he would continue to hold his position."}, {"nid": 1781538743641, "word": "征地", "meaning": "to requisition land", "sentence": "政府为了修路开始征地。", "pinyin": "Zhèngfǔ wèile xiū lù kāishǐ zhēngdì.", "english": "The government began requisitioning land to build a road."}, {"nid": 1781538743646, "word": "达致", "meaning": "to attain; to achieve", "sentence": "双方经过协商，达致了共同协议。", "pinyin": "Shuāngfāng jīngguò xiéshāng, dázhìle gòngtóng xiéyì.", "english": "After negotiation, both sides attained a mutual agreement."}, {"nid": 1781538743649, "word": "山歌", "meaning": "folk song; mountain song", "sentence": "她唱起了家乡的山歌，声音很美。", "pinyin": "Tā chàng qǐ le jiāxiāng de shāngē, shēngyīn hěn měi.", "english": "She sang a folk song from her hometown in a beautiful voice."}]