[{"nid": 1781538470898, "word": "微电脑", "meaning": "microcomputer", "sentence": "这台洗衣机内置微电脑控制系统。", "pinyin": "Zhè tái xǐyījī nèizhì wēi diàn nǎo kòngzhì xìtǒng.", "english": "This washing machine has a built-in microcomputer control system."}, {"nid": 1781538470900, "word": "券商", "meaning": "securities dealer; share broker", "sentence": "他在一家知名券商工作，专门做股票分析。", "pinyin": "Tā zài yī jiā zhīmíng quàn shāng gōngzuò, zhuānmén zuò gǔpiào fēnxī.", "english": "He works at a well-known securities dealer specializing in stock analysis."}, {"nid": 1781538470901, "word": "代为", "meaning": "to do sth on behalf of sb else", "sentence": "他不在，我可以代为签收快递。", "pinyin": "Tā bù zài, wǒ kěyǐ dài wéi qiān shōu kuàidì.", "english": "He's not here — I can sign for the delivery on his behalf."}, {"nid": 1781538470903, "word": "圣体", "meaning": "the Emperor's body; Jesus' body; communion wafer (in Christian mass)", "sentence": "信徒在弥撒中领受圣体。", "pinyin": "Xìntú zài mísā zhōng lǐngshòu shèng tǐ.", "english": "Believers receive communion during Mass."}, {"nid": 1781538470904, "word": "纯爱", "meaning": "pure love; BL, aka boys' love (genre of male homoerotic fictional medi", "sentence": "这部小说描写了两个人之间的纯爱故事。", "pinyin": "Zhè bù xiǎoshuō miáoxiě le liǎng gè rén zhījiān de chún ài gùshi.", "english": "This novel tells a story of pure love between two people."}]